dhruv/__init__.py
dhruv/cli.py
dhruv/main.py
dhruv/utils/ascii_banners.py
dhruv/utils/banner.py
dhruv/utils/syntax_themes.py
dhruv-2.0.0.dist-info/METADATA
dhruv-2.0.0.dist-info/WHEEL
dhruv-2.0.0.dist-info/entry_points.txt
dhruv-2.0.0.dist-info/top_level.txt
dhruv-2.0.0.dist-info/RECORD
