Metadata-Version: 2.4
Name: dhruv
Version: 2.0.0
Summary: A Python package
Author: dhruv13x
License: MIT
Project-URL: Homepage, https://github.com/dhruv13x/dhruv
Project-URL: Repository, https://github.com/dhruv13x/dhruv
Requires-Python: >=3.8
Requires-Dist: typer
Requires-Dist: rich
